{
    "os": "Linux-5.15.0-72-generic-x86_64-with-glibc2.31",
    "python": "3.9.16",
    "heartbeatAt": "2023-05-31T04:35:42.788669",
    "startedAt": "2023-05-31T04:35:41.095051",
    "docker": null,
    "cuda": null,
    "args": [
        "--max_steps",
        "10",
        "--start_training",
        "5"
    ],
    "state": "running",
    "program": "/home/howard/RLproject/train_finetuning.py",
    "codePath": "train_finetuning.py",
    "git": {
        "remote": "https://github.com/ttopeor/RLproject.git",
        "commit": "c6b0157a811b789ad642efe5e386fed3b1dceb37"
    },
    "email": "chehao27@uw.edu",
    "root": "/home/howard/RLproject",
    "host": "howard-Stealth-15M-A11SEK",
    "username": "howard",
    "executable": "/home/howard/anaconda3/envs/rlpd/bin/python",
    "cpu_count": 4,
    "cpu_count_logical": 8,
    "cpu_freq": {
        "current": 2911.7435,
        "min": 400.0,
        "max": 4800.0
    },
    "cpu_freq_per_core": [
        {
            "current": 3000.0,
            "min": 400.0,
            "max": 4800.0
        },
        {
            "current": 3000.0,
            "min": 400.0,
            "max": 4800.0
        },
        {
            "current": 3000.0,
            "min": 400.0,
            "max": 4800.0
        },
        {
            "current": 3000.0,
            "min": 400.0,
            "max": 4800.0
        },
        {
            "current": 3000.0,
            "min": 400.0,
            "max": 4800.0
        },
        {
            "current": 3000.0,
            "min": 400.0,
            "max": 4800.0
        },
        {
            "current": 2293.948,
            "min": 400.0,
            "max": 4800.0
        },
        {
            "current": 3000.0,
            "min": 400.0,
            "max": 4800.0
        }
    ],
    "disk": {
        "total": 365.1813850402832,
        "used": 48.85875701904297
    },
    "gpu": "NVIDIA GeForce RTX 2060 with Max-Q Design",
    "gpu_count": 1,
    "gpu_devices": [
        {
            "name": "NVIDIA GeForce RTX 2060 with Max-Q Design",
            "memory_total": 6442450944
        }
    ],
    "memory": {
        "total": 15.335796356201172
    }
}
